cyclops/__init__.py
cyclops/cyclops.py
kyklop/__init__.py
kyklop/kyklop.py
kyklop-0.1.1.dist-info/top_level.txt
kyklop-0.1.1.dist-info/METADATA
kyklop-0.1.1.dist-info/entry_points.txt
kyklop-0.1.1.dist-info/DESCRIPTION.rst
kyklop-0.1.1.dist-info/metadata.json
kyklop-0.1.1.dist-info/WHEEL
kyklop-0.1.1.dist-info/RECORD
